{
"type": "FeatureCollection",
"crs": { "type": "name", "properties": { "name": "urn:ogc:def:crs:OGC:1.3:CRS84" } },
                                                                                
"features": [
{ "type": "Feature", "properties": { "Full_Name": "District 6", "dist": "D06" }, "geometry": { "type": "Point", "coordinates": [ 36.335065636270144, 32.294816242375759 ] } },
{ "type": "Feature", "properties": { "Full_Name": "District 2", "dist": "D02" }, "geometry": { "type": "Point", "coordinates": [ 36.31654203029052, 32.298223586549341 ] } },
{ "type": "Feature", "properties": { "Full_Name": "District 12", "dist": "D12" }, "geometry": { "type": "Point", "coordinates": [ 36.315166355343081, 32.293702105567775 ] } },
{ "type": "Feature", "properties": { "Full_Name": "District 1", "dist": "D01" }, "geometry": { "type": "Point", "coordinates": [ 36.318883103172709, 32.301984851719567 ] } },
{ "type": "Feature", "properties": { "Full_Name": "District 11", "dist": "D11" }, "geometry": { "type": "Point", "coordinates": [ 36.320482223675754, 32.291003705956314 ] } },
{ "type": "Feature", "properties": { "Full_Name": "District 8", "dist": "D08" }, "geometry": { "type": "Point", "coordinates": [ 36.33786526986637, 32.285106021225943 ] } },
{ "type": "Feature", "properties": { "Full_Name": "District 9", "dist": "D09" }, "geometry": { "type": "Point", "coordinates": [ 36.331687898677615, 32.287229887149635 ] } },
{ "type": "Feature", "properties": { "Full_Name": "District 10", "dist": "D10" }, "geometry": { "type": "Point", "coordinates": [ 36.326302439905703, 32.288995286903003 ] } },
{ "type": "Feature", "properties": { "Full_Name": "District 4", "dist": "D04" }, "geometry": { "type": "Point", "coordinates": [ 36.322668536723654, 32.296330062182676 ] } },
{ "type": "Feature", "properties": { "Full_Name": "District 3", "dist": "D03" }, "geometry": { "type": "Point", "coordinates": [ 36.324614325191021, 32.300655973894152 ] } },
{ "type": "Feature", "properties": { "Full_Name": "District 5", "dist": "D05" }, "geometry": { "type": "Point", "coordinates": [ 36.329680885264679, 32.29677240272423 ] } },
{ "type": "Feature", "properties": { "Full_Name": "District 7", "dist": "D07" }, "geometry": { "type": "Point", "coordinates": [ 36.340297840672861, 32.292372206112475 ] } }
]
}
